markdowndeck/__init__.py
markdowndeck/cli.py
markdowndeck/api/__init__.py
markdowndeck/api/api_client.py
markdowndeck/api/api_generator.py
markdowndeck/api/auth.py
markdowndeck/api/validation.py
markdowndeck/api/request_builders/__init__.py
markdowndeck/api/request_builders/base_builder.py
markdowndeck/api/request_builders/code_builder.py
markdowndeck/api/request_builders/list_builder.py
markdowndeck/api/request_builders/media_builder.py
markdowndeck/api/request_builders/slide_builder.py
markdowndeck/api/request_builders/table_builder.py
markdowndeck/api/request_builders/text_builder.py
markdowndeck/layout/__init__.py
markdowndeck/layout/constants.py
markdowndeck/layout/calculator/__init__.py
markdowndeck/layout/calculator/base.py
markdowndeck/layout/calculator/element_utils.py
markdowndeck/layout/calculator/section_layout.py
markdowndeck/layout/metrics/__init__.py
markdowndeck/layout/metrics/base.py
markdowndeck/layout/metrics/code.py
markdowndeck/layout/metrics/font_metrics.py
markdowndeck/layout/metrics/image.py
markdowndeck/layout/metrics/list.py
markdowndeck/layout/metrics/table.py
markdowndeck/layout/metrics/text.py
markdowndeck/models/__init__.py
markdowndeck/models/constants.py
markdowndeck/models/deck.py
markdowndeck/models/slide.py
markdowndeck/models/elements/__init__.py
markdowndeck/models/elements/base.py
markdowndeck/models/elements/code.py
markdowndeck/models/elements/list.py
markdowndeck/models/elements/media.py
markdowndeck/models/elements/table.py
markdowndeck/models/elements/text.py
markdowndeck/overflow/__init__.py
markdowndeck/overflow/constants.py
markdowndeck/overflow/detector.py
markdowndeck/overflow/handlers.py
markdowndeck/overflow/manager.py
markdowndeck/overflow/slide_builder.py
markdowndeck/parser/__init__.py
markdowndeck/parser/slide_extractor.py
markdowndeck/parser/content/__init__.py
markdowndeck/parser/content/content_parser.py
markdowndeck/parser/content/element_factory.py
markdowndeck/parser/content/formatters/__init__.py
markdowndeck-0.1.4.dist-info/METADATA
markdowndeck-0.1.4.dist-info/WHEEL
markdowndeck-0.1.4.dist-info/RECORD
