Metadata-Version: 2.4
Name: markdowndeck
Version: 0.1.4
Summary: Convert Markdown to Google Slides presentations
Author-email: Arclio Team <info@arclio.com>
License: MIT
Keywords: google slides,markdown,presentations,slides
Classifier: Development Status :: 4 - Beta
Classifier: Intended Audience :: Developers
Classifier: Intended Audience :: Information Technology
Classifier: License :: OSI Approved :: MIT License
Classifier: Programming Language :: Python :: 3
Classifier: Programming Language :: Python :: 3.10
Classifier: Programming Language :: Python :: 3.11
Classifier: Topic :: Office/Business :: Office Suites
Classifier: Topic :: Text Processing :: Markup
Requires-Python: >=3.10
Requires-Dist: google-api-python-client>=2.0.0
Requires-Dist: google-auth-oauthlib>=1.0.0
Requires-Dist: google-auth>=2.0.0
Requires-Dist: markdown-it-py>=3.0.0
Requires-Dist: pillow>=10.0.0
Requires-Dist: python-dotenv>=1.0.0
Requires-Dist: requests>=2.28.0
Provides-Extra: dev
